{
	"info": {
		"_postman_id": "a802139c-9c04-41c4-916d-df9632ccba48",
		"name": "Customer-contact-list",
		"schema": "https://schema.getpostman.com/json/collection/v2.1.0/collection.json"
	},
	"item": [
		{
			"name": "get ocp  dev",
			"request": {
				"method": "GET",
				"header": [],
				"url": {
					"raw": ""
				}
			},
			"response": []
		},
		{
			"name": "get ocp  QA",
			"request": {
				"method": "GET",
				"header": [],
				"url": {
					"raw": ""
				}
			},
			"response": []
		}
	],
	"protocolProfileBehavior": {}
}